amsdal_glue_connections/__about__.py
amsdal_glue_connections/__init__.py
amsdal_glue_connections/py.typed
amsdal_glue_connections/elasticsearch_connection/__init__.py
amsdal_glue_connections/elasticsearch_connection/sync_connection.py
amsdal_glue_connections/sql/__init__.py
amsdal_glue_connections/sql/constants.py
amsdal_glue_connections/sql/connections/__init__.py
amsdal_glue_connections/sql/connections/csv_connection/__init__.py
amsdal_glue_connections/sql/connections/csv_connection/sync_connection.py
amsdal_glue_connections/sql/connections/postgres_connection/__init__.py
amsdal_glue_connections/sql/connections/postgres_connection/async_connection.py
amsdal_glue_connections/sql/connections/postgres_connection/base.py
amsdal_glue_connections/sql/connections/postgres_connection/sync_connection.py
amsdal_glue_connections/sql/connections/sqlite_connection/__init__.py
amsdal_glue_connections/sql/connections/sqlite_connection/async_connection.py
amsdal_glue_connections/sql/connections/sqlite_connection/base.py
amsdal_glue_connections/sql/connections/sqlite_connection/sync_connection.py
amsdal_glue_connections/sql/sql_builders/__init__.py
amsdal_glue_connections/sql/sql_builders/build_expression.py
amsdal_glue_connections/sql/sql_builders/build_field.py
amsdal_glue_connections/sql/sql_builders/build_only_constructor.py
amsdal_glue_connections/sql/sql_builders/command_builder.py
amsdal_glue_connections/sql/sql_builders/exceptions.py
amsdal_glue_connections/sql/sql_builders/math_operator_transform.py
amsdal_glue_connections/sql/sql_builders/nested_field_transform.py
amsdal_glue_connections/sql/sql_builders/operator_constructor.py
amsdal_glue_connections/sql/sql_builders/query_builder.py
amsdal_glue_connections/sql/sql_builders/schema_builder.py
amsdal_glue_connections/sql/sql_builders/transform.py
amsdal_glue_connections/sql/sql_builders/postgres_utils/__init__.py
amsdal_glue_connections/sql/sql_builders/postgres_utils/cast.py
amsdal_glue_connections-0.1.23.dist-info/METADATA
amsdal_glue_connections-0.1.23.dist-info/WHEEL
amsdal_glue_connections-0.1.23.dist-info/licenses/LICENSE.txt
amsdal_glue_connections-0.1.23.dist-info/licenses/NOTICE.txt
amsdal_glue_connections-0.1.23.dist-info/RECORD
