Metadata-Version: 2.4
Name: amsdal-glue-connections
Version: 0.1.23
Summary: AMSDAL Glue connections implementation.
Project-URL: Documentation, https://github.com/amsdal/amsdal-glue?tab=readme-ov-file#amsdal-glue-project
Project-URL: Issues, https://github.com/amsdal/amsdal-glue/issues
Project-URL: Source, https://github.com/amsdal/amsdal-glue/
License:                                  Apache License
License-File: LICENSE.txt
License-File: NOTICE.txt
Classifier: Development Status :: 4 - Beta
Classifier: Programming Language :: Python
Classifier: Programming Language :: Python :: 3.10
Classifier: Programming Language :: Python :: 3.11
Classifier: Programming Language :: Python :: 3.12
Classifier: Programming Language :: Python :: Implementation :: CPython
Classifier: Programming Language :: Python :: Implementation :: PyPy
Requires-Python: >=3.10
Requires-Dist: amsdal-glue-core>=0.1.0
Provides-Extra: async-sqlite
Requires-Dist: aiosqlite>=0.20.0; extra == 'async-sqlite'
Provides-Extra: csv
Requires-Dist: pandas>=2.2.3; extra == 'csv'
Provides-Extra: elasticsearch
Requires-Dist: elasticsearch<9.0.0,>=8.18.1; extra == 'elasticsearch'
Provides-Extra: postgres-binary
Requires-Dist: psycopg[binary,pool]>=3.2.1; extra == 'postgres-binary'
Provides-Extra: postgres-c
Requires-Dist: psycopg[c,pool]>=3.2.1; extra == 'postgres-c'
